casm/project/_ClexDescription.py
casm/project/_CompositionAxes.py
casm/project/_ConfigCompositionCalculator.py
casm/project/_DirectoryStructure.py
casm/project/_Project.py
casm/project/_ProjectSettings.py
casm/project/__init__.py
casm/project/_methods.py
casm/project/_misc.py
casm/project/_symgroup.py
casm/project/ase_utils.py
casm/project/json_io.py
casm/project/bset/_BsetCommand.py
casm/project/bset/_BsetData.py
casm/project/bset/_ConfigCorrCalculator.py
casm/project/bset/__init__.py
casm/project/bset/_display_bset.py
casm/project/bset/_print_bset.py
casm/project/calc/_CalcCommand.py
casm/project/calc/_CalcData.py
casm/project/calc/__init__.py
casm/project/enum/_ConfigEnumRunner.py
casm/project/enum/_ConfigSelection.py
casm/project/enum/_EnumCommand.py
casm/project/enum/_EnumData.py
casm/project/enum/__init__.py
casm/project/fit/_FitCommand.py
casm/project/fit/_FittingData.py
casm/project/fit/__init__.py
casm/project/plot/_ConfigurationListDashboard.py
casm/project/plot/_ConfigurationSetDashboard.py
casm/project/plot/_ConfigurationSetDashboard_v2.py
casm/project/plot/_DashboardStyles.py
casm/project/plot/_ProjectionView.py
casm/project/plot/_StructureDashboard.py
casm/project/plot/_ViewAtomicStructure.py
casm/project/plot/_ViewControl.py
casm/project/plot/__init__.py
casm/project/plot/_cache.py
casm/project/plot/_misc.py
casm/project/plot/_server.py
casm/project/plot/_view.py
casm/project/plot/default_component_params.json
casm/project/structure_import/_StructureImportCommand.py
casm/project/structure_import/_StructureImportData.py
casm/project/structure_import/__init__.py
casm/project/structure_import/_methods.py
casm/project/sym/_SymCommand.py
casm/project/sym/__init__.py
casm/project/system/_SystemCommand.py
casm/project/system/_SystemData.py
casm/project/system/__init__.py
casm/vis/__init__.py
casm/vis/_api_server.py
casm/vis/_bokeh_server.py
casm/vis/_casm_vis.py
casm/vis/_functions.py
casm/vis/_vis_server.py
casm/vis/dist/index.html
casm_project-2.0a1.dist-info/licenses/LICENSE
casm_project-2.0a1.dist-info/METADATA
casm_project-2.0a1.dist-info/WHEEL
casm_project-2.0a1.dist-info/entry_points.txt
casm_project-2.0a1.dist-info/top_level.txt
casm_project-2.0a1.dist-info/RECORD
