Metadata-Version: 2.4
Name: casm-project
Version: 2.0a1
Summary: CASM project interface
Author-email: CASM developers <casm-developers@lists.engr.ucsb.edu>
License: LGPL2.1+
Project-URL: Homepage, https://prisms-center.github.io/CASMcode_docs/
Project-URL: Repository, https://github.com/prisms-center/casm_project
Classifier: Development Status :: 3 - Alpha
Classifier: Programming Language :: Python :: 3
Classifier: License :: OSI Approved :: GNU Lesser General Public License v2 or later (LGPLv2+)
Classifier: Topic :: Scientific/Engineering
Requires-Python: >=3.9
License-File: LICENSE
Requires-Dist: bokeh
Requires-Dist: darkdetect
Requires-Dist: flask
Requires-Dist: flask_cors
Requires-Dist: gunicorn
Requires-Dist: latex2mathml
Requires-Dist: numpy
Requires-Dist: scipy
Requires-Dist: libcasm-mapping>=2.3.0
Requires-Dist: libcasm-clexmonte>=2.2.0
Requires-Dist: casm-bset>=2.1.0
Requires-Dist: casm-tools>=2.0a2
Dynamic: license-file
